Metadata-Version: 2.1
Name: MGPLibraryRU24
Version: 0.1.0
Summary: Описание вашей библиотеки
Home-page: https://github.com/ваш_репозиторий
Author: VSDragon1239
Author-email: ваш.email@example.com
License: UNKNOWN
Platform: UNKNOWN
Classifier: Programming Language :: Python :: 3
Classifier: License :: OSI Approved :: MIT License
Requires-Python: >=3.6
